tests/unit_tests/__init__.py
tests/unit_tests/test_webviz_factory_registry.py
tests/unit_tests/test_webviz_instance_info.py
tests/unit_tests/test_webviz_settings.py
webviz_config/__init__.py
webviz_config/__main__.py
webviz_config/_build_webviz.py
webviz_config/_config_parser.py
webviz_config/_deprecation_store.py
webviz_config/_is_reload_process.py
webviz_config/_localhost_token.py
webviz_config/_oauth2.py
webviz_config/_plugin_abc.py
webviz_config/_shared_settings_subscriptions.py
webviz_config/_theme_class.py
webviz_config/_user_data_dir.py
webviz_config/_user_preferences.py
webviz_config/_webviz_settings_class.py
webviz_config/_write_script.py
webviz_config/command_line.py
webviz_config/common_cache.py
webviz_config/deprecation_decorators.py
webviz_config/py.typed
webviz_config/webviz_assets.py
webviz_config/webviz_factory.py
webviz_config/webviz_factory_registry.py
webviz_config/webviz_instance_info.py
webviz_config/webviz_store.py
webviz_config/_deployment/__init__.py
webviz_config/_deployment/azure_cli.py
webviz_config/_deployment/azure_configuration.py
webviz_config/_deployment/github_cli.py
webviz_config/_deployment/interactive_terminal.py
webviz_config/_deployment/radix.py
webviz_config/_deployment/radix_cli.py
webviz_config/_deployment/radix_configuration.py
webviz_config/_dockerize/__init__.py
webviz_config/_dockerize/_create_docker_setup.py
webviz_config/_dockerize/_pip_git_url.py
webviz_config/_docs/__init__.py
webviz_config/_docs/_build_docs.py
webviz_config/_docs/_create_schema.py
webviz_config/_docs/open_docs.py
webviz_config/_docs/static/INTRODUCTION.md
webviz_config/_docs/static/README.md
webviz_config/_docs/static/docsify-copy-code.min.js
webviz_config/_docs/static/docsify-katex.js
webviz_config/_docs/static/docsify-tabs.min.js
webviz_config/_docs/static/docsify.min.js
webviz_config/_docs/static/index.html
webviz_config/_docs/static/katex.min.css
webviz_config/_docs/static/prism-bash.min.js
webviz_config/_docs/static/prism-python.min.js
webviz_config-0.6.6.dist-info/LICENSE
webviz_config-0.6.6.dist-info/LICENSE.chromedriver
webviz_config-0.6.6.dist-info/METADATA
webviz_config-0.6.6.dist-info/WHEEL
webviz_config-0.6.6.dist-info/entry_points.txt
webviz_config-0.6.6.dist-info/top_level.txt
webviz_config-0.6.6.dist-info/RECORD
