Metadata-Version: 2.1
Name: webviz-config
Version: 0.6.6
Summary: Configuration file support for webviz
Home-page: https://github.com/equinor/webviz-config
Author: R&T Equinor
Project-URL: Documentation, https://equinor.github.io/webviz-config
Project-URL: Download, https://pypi.org/project/webviz-config
Project-URL: Source, https://github.com/equinor/webviz-config
Project-URL: Tracker, https://github.com/equinor/webviz-config/issues
Classifier: Programming Language :: Python :: 3
Classifier: Operating System :: OS Independent
Classifier: Natural Language :: English
Classifier: Environment :: Web Environment
Classifier: Framework :: Dash
Classifier: Framework :: Flask
Classifier: Topic :: Multimedia :: Graphics
Classifier: Topic :: Scientific/Engineering
Classifier: Topic :: Scientific/Engineering :: Visualization
Classifier: License :: OSI Approved :: MIT License
Requires-Python: ~=3.8
License-File: LICENSE
License-File: LICENSE.chromedriver
Requires-Dist: bleach[css]>=5
Requires-Dist: cryptography>=2.4
Requires-Dist: dash>=2.0
Requires-Dist: dash-pivottable>=0.0.2
Requires-Dist: flask>=2.0
Requires-Dist: flask-caching>=1.4
Requires-Dist: flask-talisman>=0.6
Requires-Dist: jinja2>=2.10
Requires-Dist: markdown>=3.0
Requires-Dist: msal>=1.5.0
Requires-Dist: orjson>=3.3
Requires-Dist: pandas>=1.0
Requires-Dist: pyarrow>=0.16
Requires-Dist: pyyaml>=5.1
Requires-Dist: requests>=2.20
Requires-Dist: tqdm>=4.8
Requires-Dist: webviz-core-components>=0.6
Requires-Dist: werkzeug>=2.0
Provides-Extra: deployment
Requires-Dist: aiohttp; extra == "deployment"
Requires-Dist: azure-core; extra == "deployment"
Requires-Dist: azure-identity; extra == "deployment"
Requires-Dist: azure-mgmt-resource; extra == "deployment"
Requires-Dist: azure-mgmt-storage; extra == "deployment"
Requires-Dist: azure-storage-blob; extra == "deployment"
Provides-Extra: tests
Requires-Dist: bandit; extra == "tests"
Requires-Dist: black<23,>=22.12; extra == "tests"
Requires-Dist: dash[testing]; extra == "tests"
Requires-Dist: jsonschema; extra == "tests"
Requires-Dist: mypy; extra == "tests"
Requires-Dist: pylint<=2.13.9; extra == "tests"
Requires-Dist: pytest-xdist; extra == "tests"
Requires-Dist: pytest-forked; extra == "tests"
Requires-Dist: selenium; extra == "tests"
Requires-Dist: types-bleach; extra == "tests"
Requires-Dist: types-markdown; extra == "tests"
Requires-Dist: types-pyyaml; extra == "tests"
Requires-Dist: types-requests; extra == "tests"
